[
{"code": "AF", "displayValue": "Afghanistan", "phonePrefix": "+93", "flagEmoji": "🇦🇫"  , "code3": "AFG"},
  {"code": "AX", "displayValue": "Åland Islands", "phonePrefix": "+358", "flagEmoji": "🇦🇽"  , "code3": "ALA"},
  {"code": "AL", "displayValue": "Albania", "phonePrefix": "+355", "flagEmoji": "🇦🇱"  , "code3": "ALB"},
  {"code": "DZ", "displayValue": "Algeria", "phonePrefix": "+213", "flagEmoji": "🇩🇿"  , "code3": "DZA"},
  {"code": "AS", "displayValue": "American Samoa", "phonePrefix": "+1", "flagEmoji": "🇦🇸"  , "code3": "ASM"},
  {"code": "AD", "displayValue": "Andorra", "phonePrefix": "+376", "flagEmoji": "🇦🇩"  , "code3": "AND"},
  {"code": "AO", "displayValue": "Angola", "phonePrefix": "+244", "flagEmoji": "🇦🇴"  , "code3": "AGO"},
  {"code": "AI", "displayValue": "Anguilla", "phonePrefix": "+1", "flagEmoji": "🇦🇮"  , "code3": "AIA"},
  {"code": "AQ", "displayValue": "Antarctica", "phonePrefix": "", "flagEmoji": "🇦🇶"  , "code3": "ATA"},
  {"code": "AG", "displayValue": "Antigua and Barbuda", "phonePrefix": "+1", "flagEmoji": "🇦🇬"  , "code3": "ATG"},
  {"code": "AR", "displayValue": "Argentina", "phonePrefix": "+54", "flagEmoji": "🇦🇷"  , "code3": "ARG"},
  {"code": "AM", "displayValue": "Armenia", "phonePrefix": "+374", "flagEmoji": "🇦🇲"  , "code3": "ARM"},
  {"code": "AW", "displayValue": "Aruba", "phonePrefix": "+297", "flagEmoji": "🇦🇼"  , "code3": "ABW"},
  {"code": "AU", "displayValue": "Australia", "phonePrefix": "+61", "flagEmoji": "🇦🇺"  , "code3": "AUS"},
  {"code": "AT", "displayValue": "Austria", "phonePrefix": "+43", "flagEmoji": "🇦🇹"  , "code3": "AUT"},
  {"code": "AZ", "displayValue": "Azerbaijan", "phonePrefix": "+994", "flagEmoji": "🇦🇿"  , "code3": "AZE"},
  {"code": "BS", "displayValue": "Bahamas", "phonePrefix": "+1", "flagEmoji": "🇧🇸"  , "code3": "BHS"},
  {"code": "BH", "displayValue": "Bahrain", "phonePrefix": "+973", "flagEmoji": "🇧🇭"  , "code3": "BHR"},
  {"code": "BD", "displayValue": "Bangladesh", "phonePrefix": "+880", "flagEmoji": "🇧🇩"  , "code3": "BGD"},
  {"code": "BB", "displayValue": "Barbados", "phonePrefix": "+1", "flagEmoji": "🇧🇧"  , "code3": "BRB"},
  {"code": "BY", "displayValue": "Belarus", "phonePrefix": "+375", "flagEmoji": "🇧🇾"  , "code3": "BLR"},
  {"code": "BE", "displayValue": "Belgium", "phonePrefix": "+32", "flagEmoji": "🇧🇪"  , "code3": "BEL"},
  {"code": "BZ", "displayValue": "Belize", "phonePrefix": "+501", "flagEmoji": "🇧🇿"  , "code3": "BLZ"},
  {"code": "BJ", "displayValue": "Benin", "phonePrefix": "+229", "flagEmoji": "🇧🇯"  , "code3": "BEN"},
  {"code": "BM", "displayValue": "Bermuda", "phonePrefix": "+1", "flagEmoji": "🇧🇲"  , "code3": "BMU"},
  {"code": "BT", "displayValue": "Bhutan", "phonePrefix": "+975", "flagEmoji": "🇧🇹"  , "code3": "BTN"},
  {"code": "BO", "displayValue": "Bolivia (Plurinational State of)", "phonePrefix": "+591", "flagEmoji": "🇧🇴"  , "code3": "BOL"},
  {"code": "BQ", "displayValue": "Bonaire, Sint Eustatius and Saba", "phonePrefix": "+599", "flagEmoji": "🇧🇶"  , "code3": "BES"},
  {"code": "BA", "displayValue": "Bosnia and Herzegovina", "phonePrefix": "+387", "flagEmoji": "🇧🇦"  , "code3": "BIH"},
  {"code": "BW", "displayValue": "Botswana", "phonePrefix": "+267", "flagEmoji": "🇧🇼"  , "code3": "BWA"},
  {"code": "BV", "displayValue": "Bouvet Island", "phonePrefix": "", "flagEmoji": "🇧🇻"  , "code3": "BVT"},
  {"code": "BR", "displayValue": "Brazil", "phonePrefix": "+55", "flagEmoji": "🇧🇷"  , "code3": "BRA"},
  {"code": "IO", "displayValue": "British Indian Ocean Territory", "phonePrefix": "+246", "flagEmoji": "🇮🇴"  , "code3": "IOT"},
  {"code": "BN", "displayValue": "Brunei Darussalam", "phonePrefix": "+673", "flagEmoji": "🇧🇳"  , "code3": "BRN"},
  {"code": "BG", "displayValue": "Bulgaria", "phonePrefix": "+359", "flagEmoji": "🇧🇬"  , "code3": "BGR"},
  {"code": "BF", "displayValue": "Burkina Faso", "phonePrefix": "+226", "flagEmoji": "🇧🇫"  , "code3": "BFA"},
  {"code": "BI", "displayValue": "Burundi", "phonePrefix": "+257", "flagEmoji": "🇧🇮"  , "code3": "BDI"},
  {"code": "CV", "displayValue": "Cabo Verde", "phonePrefix": "+238", "flagEmoji": "🇨🇻"  , "code3": "CPV"},
  {"code": "KH", "displayValue": "Cambodia", "phonePrefix": "+855", "flagEmoji": "🇰🇭"  , "code3": "KHM"},
  {"code": "CM", "displayValue": "Cameroon", "phonePrefix": "+237", "flagEmoji": "🇨🇲"  , "code3": "CMR"},
  {"code": "CA", "displayValue": "Canada", "phonePrefix": "+1", "flagEmoji": "🇨🇦"  , "code3": "CAN"},
  {"code": "KY", "displayValue": "Cayman Islands", "phonePrefix": "+1", "flagEmoji": "🇰🇾"  , "code3": "CYM"},
  {"code": "CF", "displayValue": "Central African Republic", "phonePrefix": "+236", "flagEmoji": "🇨🇫"  , "code3": "CAF"},
  {"code": "TD", "displayValue": "Chad", "phonePrefix": "+235", "flagEmoji": "🇹🇩"  , "code3": "TCD"},
  {"code": "CL", "displayValue": "Chile", "phonePrefix": "+56", "flagEmoji": "🇨🇱"  , "code3": "CHL"},
  {"code": "CN", "displayValue": "China", "phonePrefix": "+86", "flagEmoji": "🇨🇳"  , "code3": "CHN"},
  {"code": "CX", "displayValue": "Christmas Island", "phonePrefix": "+61", "flagEmoji": "🇨🇽"  , "code3": "CXR"},
  {"code": "CC", "displayValue": "Cocos (Keeling) Islands", "phonePrefix": "+61", "flagEmoji": "🇨🇨"  , "code3": "CCK"},
  {"code": "CO", "displayValue": "Colombia", "phonePrefix": "+57", "flagEmoji": "🇨🇴"  , "code3": "COL"},
  {"code": "KM", "displayValue": "Comoros", "phonePrefix": "+269", "flagEmoji": "🇰🇲"  , "code3": "COM"},
  {"code": "CG", "displayValue": "Congo", "phonePrefix": "+242", "flagEmoji": "🇨🇬"  , "code3": "COD"},
  {"code": "CD", "displayValue": "Congo (Democratic Republic of the)", "phonePrefix": "+243", "flagEmoji": "🇨🇩"  , "code3": "COG"},
  {"code": "CK", "displayValue": "Cook Islands", "phonePrefix": "+682", "flagEmoji": "🇨🇰"  , "code3": "COK"},
  {"code": "CR", "displayValue": "Costa Rica", "phonePrefix": "+506", "flagEmoji": "🇨🇷"  , "code3": "CRI"},
  {"code": "CI", "displayValue": "Côte d'Ivoire", "phonePrefix": "+225", "flagEmoji": "🇨🇮"  , "code3": "CIV"},
  {"code": "HR", "displayValue": "Croatia", "phonePrefix": "+385", "flagEmoji": "🇭🇷"  , "code3": "HRV"},
  {"code": "CU", "displayValue": "Cuba", "phonePrefix": "+53", "flagEmoji": "🇨🇺"  , "code3": "CUB"},
  {"code": "CW", "displayValue": "Curaçao", "phonePrefix": "+599", "flagEmoji": "🇨🇼"  , "code3": "CUW"},
  {"code": "CY", "displayValue": "Cyprus", "phonePrefix": "+357", "flagEmoji": "🇨🇾"  , "code3": "CYP"},
  {"code": "CZ", "displayValue": "Czechia", "phonePrefix": "+420", "flagEmoji": "🇨🇿"  , "code3": "CZE"},
  {"code": "DK", "displayValue": "Denmark", "phonePrefix": "+45", "flagEmoji": "🇩🇰"  , "code3": "DNK"},
  {"code": "DJ", "displayValue": "Djibouti", "phonePrefix": "+253", "flagEmoji": "🇩🇯"  , "code3": "DJI"},
  {"code": "DM", "displayValue": "Dominica", "phonePrefix": "+1", "flagEmoji": "🇩🇲"  , "code3": "DMA"},
  {"code": "DO", "displayValue": "Dominican Republic", "phonePrefix": "+1", "flagEmoji": "🇩🇴"  , "code3": "DOM"},
  {"code": "EC", "displayValue": "Ecuador", "phonePrefix": "+593", "flagEmoji": "🇪🇨"  , "code3": "ECU"},
  {"code": "EG", "displayValue": "Egypt", "phonePrefix": "+20", "flagEmoji": "🇪🇬"  , "code3": "EGY"},
  {"code": "SV", "displayValue": "El Salvador", "phonePrefix": "+503", "flagEmoji": "🇸🇻"  , "code3": "SLV"},
  {"code": "GQ", "displayValue": "Equatorial Guinea", "phonePrefix": "+240", "flagEmoji": "🇬🇶"  , "code3": "GNQ"},
  {"code": "ER", "displayValue": "Eritrea", "phonePrefix": "+291", "flagEmoji": "🇪🇷"  , "code3": "ERI"},
  {"code": "EE", "displayValue": "Estonia", "phonePrefix": "+372", "flagEmoji": "🇪🇪"  , "code3": "EST"},
  {"code": "SZ", "displayValue": "Eswatini", "phonePrefix": "+268", "flagEmoji": "🇸🇿"  , "code3": "SWZ"},
  {"code": "ET", "displayValue": "Ethiopia", "phonePrefix": "+251", "flagEmoji": "🇪🇹"  , "code3": "ETH"},
  {"code": "FK", "displayValue": "Falkland Islands (Malvinas)", "phonePrefix": "+500", "flagEmoji": "🇫🇰"  , "code3": "FLK"},
  {"code": "FO", "displayValue": "Faroe Islands", "phonePrefix": "+298", "flagEmoji": "🇫🇴"  , "code3": "FRO"},
  {"code": "FJ", "displayValue": "Fiji", "phonePrefix": "+679", "flagEmoji": "🇫🇯"  , "code3": "FJI"},
  {"code": "FI", "displayValue": "Finland", "phonePrefix": "+358", "flagEmoji": "🇫🇮"  , "code3": "FIN"},
  {"code": "FR", "displayValue": "France", "phonePrefix": "+33", "flagEmoji": "🇫🇷"  , "code3": "FRA"},
  {"code": "GF", "displayValue": "French Guiana", "phonePrefix": "+594", "flagEmoji": "🇬🇫"  , "code3": "GUF"},
  {"code": "PF", "displayValue": "French Polynesia", "phonePrefix": "+689", "flagEmoji": "🇵🇫"  , "code3": "PYF"},
  {"code": "TF", "displayValue": "French Southern Territories", "phonePrefix": "", "flagEmoji": "🇹🇫"  , "code3": "ATF"},
  {"code": "GA", "displayValue": "Gabon", "phonePrefix": "+241", "flagEmoji": "🇬🇦"  , "code3": "GAB"},
  {"code": "GM", "displayValue": "Gambia", "phonePrefix": "+220", "flagEmoji": "🇬🇲"  , "code3": "GMB"},
  {"code": "GE", "displayValue": "Georgia", "phonePrefix": "+995", "flagEmoji": "🇬🇪"  , "code3": "GEO"},
  {"code": "DE", "displayValue": "Germany", "phonePrefix": "+49", "flagEmoji": "🇩🇪"  , "code3": "DEU"},
  {"code": "GH", "displayValue": "Ghana", "phonePrefix": "+233", "flagEmoji": "🇬🇭"  , "code3": "GHA"},
  {"code": "GI", "displayValue": "Gibraltar", "phonePrefix": "+350", "flagEmoji": "🇬🇮"  , "code3": "GIB"},
  {"code": "GR", "displayValue": "Greece", "phonePrefix": "+30", "flagEmoji": "🇬🇷"  , "code3": "GRC"},
  {"code": "GL", "displayValue": "Greenland", "phonePrefix": "+299", "flagEmoji": "🇬🇱"  , "code3": "GRL"},
  {"code": "GD", "displayValue": "Grenada", "phonePrefix": "+1", "flagEmoji": "🇬🇩"  , "code3": "GRD"},
  {"code": "GP", "displayValue": "Guadeloupe", "phonePrefix": "+590", "flagEmoji": "🇬🇵"  , "code3": "GLP"},
  {"code": "GU", "displayValue": "Guam", "phonePrefix": "+1", "flagEmoji": "🇬🇺"  , "code3": "GUM"},
  {"code": "GT", "displayValue": "Guatemala", "phonePrefix": "+502", "flagEmoji": "🇬🇹"  , "code3": "GTM"},
  {"code": "GG", "displayValue": "Guernsey", "phonePrefix": "+44", "flagEmoji": "🇬🇬"  , "code3": "GGY"},
  {"code": "GN", "displayValue": "Guinea", "phonePrefix": "+224", "flagEmoji": "🇬🇳"  , "code3": "GIN"},
  {"code": "GW", "displayValue": "Guinea-Bissau", "phonePrefix": "+245", "flagEmoji": "🇬🇼"  , "code3": "GNB"},
  {"code": "GY", "displayValue": "Guyana", "phonePrefix": "+592", "flagEmoji": "🇬🇾"  , "code3": "GUY"},
  {"code": "HT", "displayValue": "Haiti", "phonePrefix": "+509", "flagEmoji": "🇭🇹"  , "code3": "HTI"},
  {"code": "HM", "displayValue": "Heard Island and McDonald Islands", "phonePrefix": "", "flagEmoji": "🇭🇲"  , "code3": "HMD"},
  {"code": "VA", "displayValue": "Holy See", "phonePrefix": "+379", "flagEmoji": "🇻🇦"  , "code3": "VAT"},
  {"code": "HN", "displayValue": "Honduras", "phonePrefix": "+504", "flagEmoji": "🇭🇳"  , "code3": "HND"},
  {"code": "HK", "displayValue": "Hong Kong", "phonePrefix": "+852", "flagEmoji": "🇭🇰"  , "code3": "HKG"},
  {"code": "HU", "displayValue": "Hungary", "phonePrefix": "+36", "flagEmoji": "🇭🇺"  , "code3": "HUN"},
  {"code": "IS", "displayValue": "Iceland", "phonePrefix": "+354", "flagEmoji": "🇮🇸"  , "code3": "ISL"},
  {"code": "IN", "displayValue": "India", "phonePrefix": "+91", "flagEmoji": "🇮🇳"  , "code3": "IND"},
  {"code": "ID", "displayValue": "Indonesia", "phonePrefix": "+62", "flagEmoji": "🇮🇩"  , "code3": "IDN"},
  {"code": "IR", "displayValue": "Iran (Islamic Republic of)", "phonePrefix": "+98", "flagEmoji": "🇮🇷"  , "code3": "IRN"},
  {"code": "IQ", "displayValue": "Iraq", "phonePrefix": "+964", "flagEmoji": "🇮🇶"  , "code3": "IRQ"},
  {"code": "IE", "displayValue": "Ireland", "phonePrefix": "+353", "flagEmoji": "🇮🇪"  , "code3": "IRL"},
  {"code": "IM", "displayValue": "Isle of Man", "phonePrefix": "+44", "flagEmoji": "🇮🇲"  , "code3": "IMN"},
  {"code": "IL", "displayValue": "Israel", "phonePrefix": "+972", "flagEmoji": "🇮🇱"  , "code3": "ISR"},
  {"code": "IT", "displayValue": "Italy", "phonePrefix": "+39", "flagEmoji": "🇮🇹"  , "code3": "ITA"},
  {"code": "JM", "displayValue": "Jamaica", "phonePrefix": "+1", "flagEmoji": "🇯🇲"  , "code3": "JAM"},
  {"code": "JP", "displayValue": "Japan", "phonePrefix": "+81", "flagEmoji": "🇯🇵"  , "code3": "JPN"},
  {"code": "JE", "displayValue": "Jersey", "phonePrefix": "+44", "flagEmoji": "🇯🇪"  , "code3": "JEY"},
  {"code": "JO", "displayValue": "Jordan", "phonePrefix": "+962", "flagEmoji": "🇯🇴"  , "code3": "JOR"},
  {"code": "KZ", "displayValue": "Kazakhstan", "phonePrefix": "+7", "flagEmoji": "🇰🇿"  , "code3": "KAZ"},
  {"code": "KE", "displayValue": "Kenya", "phonePrefix": "+254", "flagEmoji": "🇰🇪"  , "code3": "KEN"},
  {"code": "KI", "displayValue": "Kiribati", "phonePrefix": "+686", "flagEmoji": "🇰🇮"  , "code3": "KIR"},
  {"code": "KP", "displayValue": "Korea (Democratic People's Republic of)", "phonePrefix": "+850", "flagEmoji": "🇰🇵"  , "code3": "PRK"},
  {"code": "KR", "displayValue": "Korea (Republic of)", "phonePrefix": "+82", "flagEmoji": "🇰🇷"  , "code3": "KOR"},
  {"code": "KW", "displayValue": "Kuwait", "phonePrefix": "+965", "flagEmoji": "🇰🇼"  , "code3": "KWT"},
  {"code": "KG", "displayValue": "Kyrgyzstan", "phonePrefix": "+996", "flagEmoji": "🇰🇬"  , "code3": "KGZ"},
  {"code": "LA", "displayValue": "Lao People's Democratic Republic", "phonePrefix": "+856", "flagEmoji": "🇱🇦"  , "code3": "LAO"},
  {"code": "LV", "displayValue": "Latvia", "phonePrefix": "+371", "flagEmoji": "🇱🇻"  , "code3": "LVA"},
  {"code": "LB", "displayValue": "Lebanon", "phonePrefix": "+961", "flagEmoji": "🇱🇧"  , "code3": "LBN"},
  {"code": "LS", "displayValue": "Lesotho", "phonePrefix": "+266", "flagEmoji": "🇱🇸"  , "code3": "LSO"},
  {"code": "LR", "displayValue": "Liberia", "phonePrefix": "+231", "flagEmoji": "🇱🇷"  , "code3": "LBR"},
  {"code": "LY", "displayValue": "Libya", "phonePrefix": "+218", "flagEmoji": "🇱🇾"  , "code3": "LBY"},
  {"code": "LI", "displayValue": "Liechtenstein", "phonePrefix": "+423", "flagEmoji": "🇱🇮"  , "code3": "LIE"},
  {"code": "LT", "displayValue": "Lithuania", "phonePrefix": "+370", "flagEmoji": "🇱🇹"  , "code3": "LTU"},
  {"code": "LU", "displayValue": "Luxembourg", "phonePrefix": "+352", "flagEmoji": "🇱🇺"  , "code3": "LUX"},
  {"code": "MO", "displayValue": "Macao", "phonePrefix": "+853", "flagEmoji": "🇲🇴"  , "code3": "MAC"},
  {"code": "MG", "displayValue": "Madagascar", "phonePrefix": "+261", "flagEmoji": "🇲🇬"  , "code3": "MDG"},
  {"code": "MW", "displayValue": "Malawi", "phonePrefix": "+265", "flagEmoji": "🇲🇼"  , "code3": "MWI"},
  {"code": "MY", "displayValue": "Malaysia", "phonePrefix": "+60", "flagEmoji": "🇲🇾"  , "code3": "MYS"},
  {"code": "MV", "displayValue": "Maldives", "phonePrefix": "+960", "flagEmoji": "🇲🇻"  , "code3": "MDV"},
  {"code": "ML", "displayValue": "Mali", "phonePrefix": "+223", "flagEmoji": "🇲🇱"  , "code3": "MLI"},
  {"code": "MT", "displayValue": "Malta", "phonePrefix": "+356", "flagEmoji": "🇲🇹"  , "code3": "MLT"},
  {"code": "MH", "displayValue": "Marshall Islands", "phonePrefix": "+692", "flagEmoji": "🇲🇭"  , "code3": "MHL"},
  {"code": "MQ", "displayValue": "Martinique", "phonePrefix": "+596", "flagEmoji": "🇲🇶"  , "code3": "MTQ"},
  {"code": "MR", "displayValue": "Mauritania", "phonePrefix": "+222", "flagEmoji": "🇲🇷"  , "code3": "MRT"},
  {"code": "MU", "displayValue": "Mauritius", "phonePrefix": "+230", "flagEmoji": "🇲🇺"  , "code3": "MUS"},
  {"code": "YT", "displayValue": "Mayotte", "phonePrefix": "+262", "flagEmoji": "🇾🇹"  , "code3": "MYT"},
  {"code": "MX", "displayValue": "Mexico", "phonePrefix": "+52", "flagEmoji": "🇲🇽"  , "code3": "MEX"},
  {"code": "FM", "displayValue": "Micronesia (Federated States of)", "phonePrefix": "+691", "flagEmoji": "🇫🇲"  , "code3": "FSM"},
  {"code": "MD", "displayValue": "Moldova (Republic of)", "phonePrefix": "+373", "flagEmoji": "🇲🇩"  , "code3": "MDA"},
  {"code": "MC", "displayValue": "Monaco", "phonePrefix": "+377", "flagEmoji": "🇲🇨"  , "code3": "MCO"},
  {"code": "MN", "displayValue": "Mongolia", "phonePrefix": "+976", "flagEmoji": "🇲🇳"  , "code3": "MNG"},
  {"code": "ME", "displayValue": "Montenegro", "phonePrefix": "+382", "flagEmoji": "🇲🇪"  , "code3": "MNE"},
  {"code": "MS", "displayValue": "Montserrat", "phonePrefix": "+1", "flagEmoji": "🇲🇸"  , "code3": "MSR"},
  {"code": "MA", "displayValue": "Morocco", "phonePrefix": "+212", "flagEmoji": "🇲🇦"  , "code3": "MAR"},
  {"code": "MZ", "displayValue": "Mozambique", "phonePrefix": "+258", "flagEmoji": "🇲🇿"  , "code3": "MOZ"},
  {"code": "MM", "displayValue": "Myanmar", "phonePrefix": "+95", "flagEmoji": "🇲🇲"  , "code3": "MMR"},
  {"code": "NA", "displayValue": "Namibia", "phonePrefix": "+264", "flagEmoji": "🇳🇦"  , "code3": "NAM"},
  {"code": "NR", "displayValue": "Nauru", "phonePrefix": "+674", "flagEmoji": "🇳🇷"  , "code3": "NRU"},
  {"code": "NP", "displayValue": "Nepal", "phonePrefix": "+977", "flagEmoji": "🇳🇵"  , "code3": "NPL"},
  {"code": "NL", "displayValue": "Netherlands", "phonePrefix": "+31", "flagEmoji": "🇳🇱"  , "code3": "NLD"},
  {"code": "NC", "displayValue": "New Caledonia", "phonePrefix": "+687", "flagEmoji": "🇳🇨"  , "code3": "NCL"},
  {"code": "NZ", "displayValue": "New Zealand", "phonePrefix": "+64", "flagEmoji": "🇳🇿"  , "code3": "NZL"},
  {"code": "NI", "displayValue": "Nicaragua", "phonePrefix": "+505", "flagEmoji": "🇳🇮"  , "code3": "NIC"},
  {"code": "NE", "displayValue": "Niger", "phonePrefix": "+227", "flagEmoji": "🇳🇪"  , "code3": "NER"},
  {"code": "NG", "displayValue": "Nigeria", "phonePrefix": "+234", "flagEmoji": "🇳🇬"  , "code3": "NGA"},
  {"code": "NU", "displayValue": "Niue", "phonePrefix": "+683", "flagEmoji": "🇳🇺"  , "code3": "NIU"},
  {"code": "NF", "displayValue": "Norfolk Island", "phonePrefix": "+672", "flagEmoji": "🇳🇫"  , "code3": "NFK"},
  {"code": "MK", "displayValue": "North Macedonia", "phonePrefix": "+389", "flagEmoji": "🇲🇰"  , "code3": "MKD"},
  {"code": "MP", "displayValue": "Northern Mariana Islands", "phonePrefix": "+1", "flagEmoji": "🇲🇵"  , "code3": "MNP"},
  {"code": "NO", "displayValue": "Norway", "phonePrefix": "+47", "flagEmoji": "🇳🇴"  , "code3": "NOR"},
  {"code": "OM", "displayValue": "Oman", "phonePrefix": "+968", "flagEmoji": "🇴🇲"  , "code3": "OMN"},
  {"code": "PK", "displayValue": "Pakistan", "phonePrefix": "+92", "flagEmoji": "🇵🇰"  , "code3": "PAK"},
  {"code": "PW", "displayValue": "Palau", "phonePrefix": "+680", "flagEmoji": "🇵🇼"  , "code3": "PLW"},
  {"code": "PS", "displayValue": "Palestine, State of", "phonePrefix": "+970", "flagEmoji": "🇵🇸"  , "code3": "PSE"},
  {"code": "PA", "displayValue": "Panama", "phonePrefix": "+507", "flagEmoji": "🇵🇦"  , "code3": "PAN"},
  {"code": "PG", "displayValue": "Papua New Guinea", "phonePrefix": "+675", "flagEmoji": "🇵🇬"  , "code3": "PNG"},
  {"code": "PY", "displayValue": "Paraguay", "phonePrefix": "+595", "flagEmoji": "🇵🇾"  , "code3": "PRY"},
  {"code": "PE", "displayValue": "Peru", "phonePrefix": "+51", "flagEmoji": "🇵🇪"  , "code3": "PER"},
  {"code": "PH", "displayValue": "Philippines", "phonePrefix": "+63", "flagEmoji": "🇵🇭"  , "code3": "PHL"},
  {"code": "PN", "displayValue": "Pitcairn", "phonePrefix": "+64", "flagEmoji": "🇵🇳"  , "code3": "PCN"},
  {"code": "PL", "displayValue": "Poland", "phonePrefix": "+48", "flagEmoji": "🇵🇱"  , "code3": "POL"},
  {"code": "PT", "displayValue": "Portugal", "phonePrefix": "+351", "flagEmoji": "🇵🇹"  , "code3": "PRT"},
  {"code": "PR", "displayValue": "Puerto Rico", "phonePrefix": "+1", "flagEmoji": "🇵🇷"  , "code3": "PRI"},
  {"code": "QA", "displayValue": "Qatar", "phonePrefix": "+974", "flagEmoji": "🇶🇦"  , "code3": "QAT"},
  {"code": "RE", "displayValue": "Réunion", "phonePrefix": "+262", "flagEmoji": "🇷🇪"  , "code3": "REU"},
  {"code": "RO", "displayValue": "Romania", "phonePrefix": "+40", "flagEmoji": "🇷🇴"  , "code3": "ROU"},
  {"code": "RU", "displayValue": "Russian Federation", "phonePrefix": "+7", "flagEmoji": "🇷🇺"  , "code3": "RUS"},
  {"code": "RW", "displayValue": "Rwanda", "phonePrefix": "+250", "flagEmoji": "🇷🇼"  , "code3": "RWA"},
  {"code": "BL", "displayValue": "Saint Barthélemy", "phonePrefix": "+590", "flagEmoji": "🇧🇱"  , "code3": "BLM"},
  {"code": "SH", "displayValue": "Saint Helena, Ascension and Tristan da Cunha", "phonePrefix": "+290", "flagEmoji": "🇸🇭"  , "code3": "SHN"},
  {"code": "KN", "displayValue": "Saint Kitts and Nevis", "phonePrefix": "+1", "flagEmoji": "🇰🇳"  , "code3": "KNA"},
  {"code": "LC", "displayValue": "Saint Lucia", "phonePrefix": "+1", "flagEmoji": "🇱🇨"  , "code3": "LCA"},
  {"code": "MF", "displayValue": "Saint Martin (French part)", "phonePrefix": "+590", "flagEmoji": "🇲🇫"  , "code3": "MAF"},
  {"code": "PM", "displayValue": "Saint Pierre and Miquelon", "phonePrefix": "+508", "flagEmoji": "🇵🇲"  , "code3": "SPM"},
  {"code": "VC", "displayValue": "Saint Vincent and the Grenadines", "phonePrefix": "+1", "flagEmoji": "🇻🇨"  , "code3": "VCT"},
  {"code": "WS", "displayValue": "Samoa", "phonePrefix": "+685", "flagEmoji": "🇼🇸"  , "code3": "WSM"},
  {"code": "SM", "displayValue": "San Marino", "phonePrefix": "+378", "flagEmoji": "🇸🇲"  , "code3": "SMR"},
  {"code": "ST", "displayValue": "Sao Tome and Principe", "phonePrefix": "+239", "flagEmoji": "🇸🇹"  , "code3": "STP"},
  {"code": "SA", "displayValue": "Saudi Arabia", "phonePrefix": "+966", "flagEmoji": "🇸🇦"  , "code3": "SAU"},
  {"code": "SN", "displayValue": "Senegal", "phonePrefix": "+221", "flagEmoji": "🇸🇳"  , "code3": "SEN"},
  {"code": "RS", "displayValue": "Serbia", "phonePrefix": "+381", "flagEmoji": "🇷🇸"  , "code3": "SRB"},
  {"code": "SC", "displayValue": "Seychelles", "phonePrefix": "+248", "flagEmoji": "🇸🇨"  , "code3": "SYC"},
  {"code": "SL", "displayValue": "Sierra Leone", "phonePrefix": "+232", "flagEmoji": "🇸🇱"  , "code3": "SLE"},
  {"code": "SG", "displayValue": "Singapore", "phonePrefix": "+65", "flagEmoji": "🇸🇬"  , "code3": "SGP"},
  {"code": "SX", "displayValue": "Sint Maarten (Dutch part)", "phonePrefix": "+1", "flagEmoji": "🇸🇽"  , "code3": "SXN"},
  {"code": "SK", "displayValue": "Slovakia", "phonePrefix": "+421", "flagEmoji": "🇸🇰"  , "code3": "SVK"},
  {"code": "SI", "displayValue": "Slovenia", "phonePrefix": "+386", "flagEmoji": "🇸🇮"  , "code3": "SVN"},
  {"code": "SB", "displayValue": "Solomon Islands", "phonePrefix": "+677", "flagEmoji": "🇸🇧"  , "code3": "SLB"},
  {"code": "SO", "displayValue": "Somalia", "phonePrefix": "+252", "flagEmoji": "🇸🇴"  , "code3": "SOM"},
  {"code": "ZA", "displayValue": "South Africa", "phonePrefix": "+27", "flagEmoji": "🇿🇦"  , "code3": "ZAF"},
  {"code": "GS", "displayValue": "South Georgia and the South Sandwich Islands", "phonePrefix": "", "flagEmoji": "🇬🇸"  , "code3": "SGS"},
  {"code": "SS", "displayValue": "South Sudan", "phonePrefix": "+211", "flagEmoji": "🇸🇸"  , "code3": "SSD"},
  {"code": "ES", "displayValue": "Spain", "phonePrefix": "+34", "flagEmoji": "🇪🇸"  , "code3": "ESP"},
  {"code": "LK", "displayValue": "Sri Lanka", "phonePrefix": "+94", "flagEmoji": "🇱🇰"  , "code3": "LKA"},
  {"code": "SD", "displayValue": "Sudan", "phonePrefix": "+249", "flagEmoji": "🇸🇩"  , "code3": "SDN"},
  {"code": "SR", "displayValue": "Suriname", "phonePrefix": "+597", "flagEmoji": "🇸🇷"  , "code3": "SYR"},
  {"code": "SJ", "displayValue": "Svalbard and Jan Mayen", "phonePrefix": "+47", "flagEmoji": "🇸🇯"  , "code3": "SJM"},
  {"code": "SE", "displayValue": "Sweden", "phonePrefix": "+46", "flagEmoji": "🇸🇪"  , "code3": "SWE"},
  {"code": "CH", "displayValue": "Switzerland", "phonePrefix": "+41", "flagEmoji": "🇨🇭"  , "code3": "CHE"},
  {"code": "SY", "displayValue": "Syrian Arab Republic", "phonePrefix": "+963", "flagEmoji": "🇸🇾"  , "code3": "SYR"},
  {"code": "TW", "displayValue": "Taiwan", "phonePrefix": "+886", "flagEmoji": "🇹🇼"  , "code3": "TWN"},
  {"code": "TJ", "displayValue": "Tajikistan", "phonePrefix": "+992", "flagEmoji": "🇹🇯"  , "code3": "TJK"},
  {"code": "TZ", "displayValue": "Tanzania (United Republic of)", "phonePrefix": "+255", "flagEmoji": "🇹🇿"  , "code3": "TZA"},
  {"code": "TH", "displayValue": "Thailand", "phonePrefix": "+66", "flagEmoji": "🇹🇭"  , "code3": "THA"},
  {"code": "TL", "displayValue": "Timor-Leste", "phonePrefix": "+670", "flagEmoji": "🇹🇱"  , "code3": "TLS"},
  {"code": "TG", "displayValue": "Togo", "phonePrefix": "+228", "flagEmoji": "🇹🇬"  , "code3": "TGO"},
  {"code": "TK", "displayValue": "Tokelau", "phonePrefix": "+690", "flagEmoji": "🇹🇰"  , "code3": "TKL"},
  {"code": "TO", "displayValue": "Tonga", "phonePrefix": "+676", "flagEmoji": "🇹🇴"  , "code3": "TON"},
  {"code": "TT", "displayValue": "Trinidad and Tobago", "phonePrefix": "+1", "flagEmoji": "🇹🇹"  , "code3": "TTO"},
  {"code": "TN", "displayValue": "Tunisia", "phonePrefix": "+216", "flagEmoji": "🇹🇳"  , "code3": "TUN"},
  {"code": "TR", "displayValue": "Turkey", "phonePrefix": "+90", "flagEmoji": "🇹🇷"  , "code3": "TUR"},
  {"code": "TM", "displayValue": "Turkmenistan", "phonePrefix": "+993", "flagEmoji": "🇹🇲"  , "code3": "TKM"},
  {"code": "TC", "displayValue": "Turks and Caicos Islands", "phonePrefix": "+1", "flagEmoji": "🇹🇨"  , "code3": "TCA"},
  {"code": "TV", "displayValue": "Tuvalu", "phonePrefix": "+688", "flagEmoji": "🇹🇻"  , "code3": "TUV"},
  {"code": "UG", "displayValue": "Uganda", "phonePrefix": "+256", "flagEmoji": "🇺🇬"  , "code3": "UGA"},
  {"code": "UA", "displayValue": "Ukraine", "phonePrefix": "+380", "flagEmoji": "🇺🇦"  , "code3": "UKR"},
  {"code": "AE", "displayValue": "United Arab Emirates", "phonePrefix": "+971", "flagEmoji": "🇦🇪"  , "code3": "ARE"},
  {"code": "GB", "displayValue": "United Kingdom of Great Britain and Northern Ireland", "phonePrefix": "+44", "flagEmoji": "🇬🇧"  , "code3": "GBR"},
  {"code": "US", "displayValue": "United States of America", "phonePrefix": "+1", "flagEmoji": "🇺🇸"  , "code3": "USA"},
  {"code": "UY", "displayValue": "Uruguay", "phonePrefix": "+598", "flagEmoji": "🇺🇾"  , "code3": "URY"},
  {"code": "UZ", "displayValue": "Uzbekistan", "phonePrefix": "+998", "flagEmoji": "🇺🇿"  , "code3": "UZB"},
  {"code": "VU", "displayValue": "Vanuatu", "phonePrefix": "+678", "flagEmoji": "🇻🇺"  , "code3": "VUT"},
  {"code": "VE", "displayValue": "Venezuela (Bolivarian Republic of)", "phonePrefix": "+58", "flagEmoji": "🇻🇪"  , "code3": "VEN"},
  {"code": "VN", "displayValue": "Viet Nam", "phonePrefix": "+84", "flagEmoji": "🇻🇳"  , "code3": "VNM"},
  {"code": "VG", "displayValue": "Virgin Islands (British)", "phonePrefix": "+1", "flagEmoji": "🇻🇬"  , "code3": "VGB"},
  {"code": "VI", "displayValue": "Virgin Islands (U.S.)", "phonePrefix": "+1", "flagEmoji": "🇻🇮"  , "code3": "VIR"},
  {"code": "WF", "displayValue": "Wallis and Futuna", "phonePrefix": "+681", "flagEmoji": "🇼🇫"  , "code3": "WLF"},
  {"code": "EH", "displayValue": "Western Sahara", "phonePrefix": "+212", "flagEmoji": "🇪🇭"  , "code3": "ESH"},
  {"code": "YE", "displayValue": "Yemen", "phonePrefix": "+967", "flagEmoji": "🇾🇪"  , "code3": "YEM"},
  {"code": "ZM", "displayValue": "Zambia", "phonePrefix": "+260", "flagEmoji": "🇿🇲"  , "code3": "ZMB"},
  {"code": "ZW", "displayValue": "Zimbabwe", "phonePrefix": "+263", "flagEmoji": "🇿🇼"  , "code3": "ZWE"}
]
